{
  "updates": {},
  "events": {
    "items": [
      {
        "Title": "#45 Ramadan Booyah 2026 - Incubator Gratis!",
        "Start": "1771153200",
        "End": "1771210799",
        "Link": "15665"
      },
      {
        "Title": "#26 Ramadan Booyah 2026 - Sambut Ramadan!",
        "Start": "1771210800",
        "End": "1771297199",
        "Link": "15666"
      },
      {
        "Title": "#15 Preheat Toko Kelontong",
        "Start": "1771124400",
        "End": "1771153199"
      },
      {
        "Title": "#14 In-game Match Event Gameplay",
        "Start": "1771038000",
        "End": "1771124399",
        "Link": "https://ff.garena.com/id/news/"
      },
      {
        "Title": "#35 Grand Finals Battle Rush ",
        "Start": "1771153200",
        "End": "1771210799",
        "Link": "https://www.youtube.com/watch?v=SJ860471yMQ"
      },
      {
        "Title": "#16 Token Ring - Flashing Spade (710000726) (Orange), Blazing Heart (710000725) (Orange)",
        "Start": "1771210800",
        "End": "1771297199",
        "Link": "V2_chestId_99"
      },
      {
        "Title": "#27 Craftland",
        "Start": "1771297200",
        "End": "1771383599",
        "Link": "V2_workshopCode_#FREEFIRED4CA60AC1AD91FD9BB16F7FBBE0FFF384913"
      },
      {
        "Title": "#25 Preheat Ramadan - Shunken Chamber",
        "Start": "1771124400",
        "End": "1771153199"
      },
      {
        "Title": "#24 Ramadan Booyah 2026 - Magic Shop Pt. 1",
        "Start": "1771038000",
        "End": "1771124399",
        "Link": "15663"
      }
    ]
  }
}