{
  "updates": {
    "items": [
      {
        "Title": "Личный Остров Комьюнити",
        "Banner": "https://dl.dir.freefiremobile.com/common/Local/IND/config/craftlandcommunity_ru.png",
        "Start": "1742158800",
        "End": "4109086799",
        "LinkAlt": "https://vk.com/club229722976"
      },
      {
        "Title": "БЫСТРЫЕ КЛИПЫ, БОЛЬШИЕ ХИТЫ!",
        "Banner": "https://dl.dir.freefiremobile.com/common/Local/IND/config/1400x700TT_ru.jpg",
        "Start": "1742763600",
        "End": "4109605199",
        "LinkAlt": "https://www.tiktok.com/@freefirecis"
      },
      {
        "Title": "Командные Ограничения",
        "Banner": "https://dl.dir.freefiremobile.com/common/Local/IND/config/SquadRestriction_NoticeRU_ru.jpg",
        "Start": "1775030400",
        "End": "1808686799"
      },
      {
        "Title": "НАБЛЮДАЙТЕ ЗА РАЗВИТИЕМ БИТВЫ",
        "Banner": "https://dl.dir.freefiremobile.com/common/Local/IND/config/1400x700YT_ru.jpg",
        "Start": "1742763600",
        "End": "4109605199",
        "LinkAlt": "https://www.youtube.com/@FreeFireRussia"
      }
    ]
  },
  "events": {
    "items": [
      {
        "Title": "Booyah Wave",
        "Start": "1776387600",
        "End": "1776473999",
        "Link": "V2_category_6_groupID_95457",
        "Banner": "https://dl.dir.freefiremobile.com/common/Local/IND/config/1750x1070_BooyahWaveRU_ru.jpg"
      },
      {
        "Title": "Step Up: UNDERSEA WHALE GLOO WALL x QUACK SHOWDOWN",
        "Start": "1776301200",
        "End": "1776387599",
        "Link": "V2_chestId_73",
        "Banner": "https://dl.dir.freefiremobile.com/common/Local/IND/config/1750x1070_StepUpUnderseaWhaleGlooWallSplashRU_ru.jpg"
      },
      {
        "Title": "Dive Time",
        "Start": "1776301200",
        "End": "1776387599",
        "Link": "V2_category_6_groupID_95458",
        "Banner": "https://dl.dir.freefiremobile.com/common/Local/IND/config/1750x1070_DriveTimeRU_ru.jpg"
      },
      {
        "Title": "Dive Time",
        "Start": "1776474000",
        "End": "1776560399",
        "Link": "V2_category_6_groupID_95458",
        "Banner": "https://dl.dir.freefiremobile.com/common/Local/IND/config/1750x1070_DriveTimeRU_ru.jpg"
      },
      {
        "Title": "Mystery Shop: VERSATILE STREETWEAR BUNDLES",
        "Start": "1776474000",
        "End": "1776560399",
        "Link": "V2",
        "Banner": "https://dl.dir.freefiremobile.com/common/Local/IND/config/1750x1070_MS_VersatileStreetRU_ru.jpg"
      },
      {
        "Title": "Undersea Mystery CG",
        "Start": "1776214800",
        "End": "1776301199",
        "Link": "https://youtu.be/Md--izNvWfs",
        "Banner": "https://dl.dir.freefiremobile.com/common/Local/IND/config/1750x1070_FullAnimationOB53RU_ru.jpg"
      },
      {
        "Title": "Undersea Ring: UNDERSEA RIPPLES BUNDLE",
        "Start": "1776387600",
        "End": "1776473999",
        "Link": "V2_chestId_89",
        "Banner": "https://dl.dir.freefiremobile.com/common/Local/IND/config/1750x1070_UnderSea_RipppleBundleRU_ru.jpg"
      },
      {
        "Title": "Mystery Shop: VERSATILE STREETWEAR BUNDLES",
        "Start": "1776214800",
        "End": "1776301199",
        "Link": "V2",
        "Banner": "https://dl.dir.freefiremobile.com/common/Local/IND/config/1750x1070_MS_VersatileStreetRU_ru.jpg"
      }
    ]
  }
}